pydbisam/__init__.py
pydbisam/cli.py
pydbisam/extract.py
pydbisam/field.py
pydbisam-1.2.1.dist-info/licenses/LICENSE
pydbisam-1.2.1.dist-info/METADATA
pydbisam-1.2.1.dist-info/WHEEL
pydbisam-1.2.1.dist-info/entry_points.txt
pydbisam-1.2.1.dist-info/top_level.txt
pydbisam-1.2.1.dist-info/RECORD
