Metadata-Version: 2.4
Name: pydbisam
Version: 1.2.1
Summary: Read DBISAM database tables.
Author-email: Aaron Linville <aaron@linville.org>
License-Expression: ISC
Project-URL: Homepage, https://github.com/linville/pydbisam/
Project-URL: Changelog, https://github.com/linville/pydbisam/blob/main/CHANGELOG.md
Project-URL: Issues, https://github.com/linville/pydbisam/issues
Keywords: dbisam
Classifier: Development Status :: 5 - Production/Stable
Classifier: Environment :: Console
Classifier: Intended Audience :: Developers
Classifier: Operating System :: OS Independent
Classifier: Programming Language :: Python :: 3
Classifier: Topic :: Database
Classifier: Topic :: Utilities
Requires-Python: >=3.9
License-File: LICENSE
Provides-Extra: dev
Requires-Dist: black==25.1.*; extra == "dev"
Requires-Dist: build==1.2.*; extra == "dev"
Requires-Dist: ruff==0.11.*; extra == "dev"
Requires-Dist: twine==6.1.*; extra == "dev"
Dynamic: license-file
